ubump-0.1.15.dist-info/METADATA
ubump-0.1.15.dist-info/WHEEL
ubump-0.1.15.dist-info/entry_points.txt
ubump-0.1.15.dist-info/licenses/LICENSE
ubump/__init__.py
ubump/main.py
ubump-0.1.15.dist-info/RECORD
