Metadata-Version: 2.1
Name: ubump
Version: 0.1.15
Summary: Yet another bump tool
Keywords: bump,bumpversion,bump2version,bump-version,bumper,bumping,version,versioning
Home-page: https://github.com/vd2org/ubump
Author-Email: vd <ubump@vd2.org>
License: Copyright 2024 Vd <ubump@vd2.org>
Classifier: Development Status :: 4 - Beta
Classifier: Intended Audience :: Developers
Classifier: Intended Audience :: Information Technology
Classifier: Intended Audience :: System Administrators
Classifier: Topic :: Software Development
Classifier: Topic :: Software Development :: Version Control
Classifier: License :: OSI Approved :: MIT License
Classifier: Programming Language :: Python :: 3.11
Classifier: Programming Language :: Python :: 3.12
Project-URL: Homepage, https://github.com/vd2org/ubump
Project-URL: Repository, https://github.com/vd2org/ubump.git
Project-URL: Issues, https://github.com/vd2org/ubump/issues
Requires-Python: <4.0,>=3.11
Requires-Dist: packaging~=23.2
Requires-Dist: tomlkit~=0.12.3
